{
  "review_type": "post_event_only",
  "model": "MiniMax-M3",
  "reviewed": 129,
  "official_ems_counts": {
    "Destroyed": 2,
    "Damaged": 34,
    "Possibly damaged": 93
  },
  "vlm_damage_class_counts": {
    "possible_major_damage": 13,
    "uncertain_imagery_problem": 93,
    "minor_visible_damage": 17,
    "no_visible_damage": 6
  },
  "vlm_action_priority_counts": {
    "review": 105,
    "urgent_review": 21,
    "deprioritize": 3
  },
  "urgent_like_count": 21,
  "warning": "VLM outputs are triage aids from post-event chips only; official EMS labels remain source of record; absence of visible VLM damage is not proof of no damage."
}
